setup.py
cmsplugin_lastfm/__init__.py
cmsplugin_lastfm/cms_plugins.py
cmsplugin_lastfm/models.py
cmsplugin_lastfm.egg-info/PKG-INFO
cmsplugin_lastfm.egg-info/SOURCES.txt
cmsplugin_lastfm.egg-info/dependency_links.txt
cmsplugin_lastfm.egg-info/not-zip-safe
cmsplugin_lastfm.egg-info/requires.txt
cmsplugin_lastfm.egg-info/top_level.txt
cmsplugin_lastfm/migrations/0001_initial.py
cmsplugin_lastfm/migrations/__init__.py