Metadata-Version: 1.0
Name: cmsplugin-lastfm
Version: 0.1.0
Summary: Django CMS Last.fm Plugins
Home-page: http://github.com/chrisglass/cmsplugin_lastfm
Author: Christopher Glass
Author-email: christopher.glass@divio.ch
License: UNKNOWN
Platform: UNKNOWN
